minisat/minisatbind.cpython-36m-x86_64-linux-gnu.so
minisat/__init__.py
minisat/.libs/libminisat-d225fca6.so
minisat-0.0.3.dist-info/WHEEL
minisat-0.0.3.dist-info/top_level.txt
minisat-0.0.3.dist-info/LICENSE
minisat-0.0.3.dist-info/METADATA
minisat-0.0.3.dist-info/RECORD
minisat-0.0.3.dist-info/entry_points.txt
