Metadata-Version: 2.1
Name: minisat
Version: 0.0.3
Summary: UNKNOWN
Home-page: https://github.com/pgdr/python-minisat
Author: pgdr
Author-email: UNKNOWN
License: UNKNOWN
Platform: UNKNOWN
Requires-Dist: scikit-build
